[
    {
        "title":"Yeongwol, Yeongheung ",
        "lat":37.183,
        "lng":128.461,
        "stratum":"Yeongheung Formation",
        "period":"Ordovician",
        "fossils":"Trilobite",
        "note":"...",
        "image":null
    },
    {
        "title":"Taebaek, Jigunsan ",
        "lat":37.105,
        "lng":129.007,
        "stratum":"Jigunsan Formation",
        "period":"Ordovician",
        "fossils":"Brachiopod",
        "note":"...",
        "image":null
    },
    {
        "title":"Mitan, Pyeonchang",
        "lat":37.203,
        "lng":128.29,
        "stratum":"Yeongheung Formation",
        "period":"Ordovician",
        "fossils":null,
        "note":null,
        "image":"images\/071000012.JPG"
    }
]
